sentineldf/__init__.py
sentineldf/__main__.py
sentineldf/chunked_scanner.py
sentineldf/cli.py
sentineldf/client.py
sentineldf/file_utils.py
sentineldf/gui.py
sentineldf/postinstall.py
sentineldf/reporting.py
sentineldf/templates/index.html
sentineldf-2.0.2.dist-info/METADATA
sentineldf-2.0.2.dist-info/WHEEL
sentineldf-2.0.2.dist-info/entry_points.txt
sentineldf-2.0.2.dist-info/top_level.txt
sentineldf-2.0.2.dist-info/RECORD
