Metadata-Version: 2.4
Name: sentineldf
Version: 2.0.2
Summary: Official Python SDK for SentinelDF - Data Firewall for LLM Training with CLI
Home-page: https://github.com/varunsripad123/sentineldf
Author: Varun Sripad Kota
Author-email: varunsripadkota@gmail.com
Project-URL: Documentation, https://docs.sentineldf.com
Project-URL: Source, https://github.com/varunsripad123/sentineldf
Project-URL: Bug Reports, https://github.com/varunsripad123/sentineldf/issues
Project-URL: Dashboard, https://sentineldf.com/dashboard
Keywords: llm security prompt-injection data-poisoning ai-safety machine-learning cli
Classifier: Development Status :: 4 - Beta
Classifier: Intended Audience :: Developers
Classifier: Topic :: Software Development :: Libraries :: Python Modules
Classifier: Topic :: Scientific/Engineering :: Artificial Intelligence
Classifier: License :: OSI Approved :: MIT License
Classifier: Programming Language :: Python :: 3
Classifier: Programming Language :: Python :: 3.8
Classifier: Programming Language :: Python :: 3.9
Classifier: Programming Language :: Python :: 3.10
Classifier: Programming Language :: Python :: 3.11
Classifier: Programming Language :: Python :: 3.12
Requires-Python: >=3.8
Requires-Dist: requests>=2.28.0
Requires-Dist: flask>=2.3.0
Provides-Extra: dev
Requires-Dist: pytest>=7.0.0; extra == "dev"
Requires-Dist: pytest-cov>=4.0.0; extra == "dev"
Requires-Dist: black>=23.0.0; extra == "dev"
Requires-Dist: flake8>=6.0.0; extra == "dev"
Requires-Dist: mypy>=1.0.0; extra == "dev"
Dynamic: author
Dynamic: author-email
Dynamic: classifier
Dynamic: description
Dynamic: description-content-type
Dynamic: home-page
Dynamic: keywords
Dynamic: project-url
Dynamic: provides-extra
Dynamic: requires-dist
Dynamic: requires-python
Dynamic: summary
